{
 "cells": [
  {
   "cell_type": "markdown",
   "metadata": {
    "slideshow": {
     "slide_type": "slide"
    }
   },
   "source": [
    "# A Light Introduction to the Internals of Python\n",
    "AI Meetup 22.05.2020"
   ]
  },
  {
   "cell_type": "markdown",
   "metadata": {
    "slideshow": {
     "slide_type": "subslide"
    }
   },
   "source": [
    "## What I won't cover in this talk:\n",
    "- lexer (source code -> tokens)\n",
    "- parser (tokens -> ast)\n",
    "- grammar (Python has a very easy grammar)\n"
   ]
  },
  {
   "cell_type": "markdown",
   "metadata": {
    "slideshow": {
     "slide_type": "subslide"
    }
   },
   "source": [
    "## Agenda\n",
    "- the cpython repository\n",
    "- compilation\n",
    "- bytecode\n",
    "- the dis module\n",
    "- opcodes\n",
    "- the ceval.c loop and Python virtual machine\n",
    "- what does it mean that in Python everything is an object"
   ]
  },
  {
   "cell_type": "markdown",
   "metadata": {
    "slideshow": {
     "slide_type": "subslide"
    }
   },
   "source": [
    "### We will be talking about Cpython"
   ]
  },
  {
   "cell_type": "markdown",
   "metadata": {
    "slideshow": {
     "slide_type": "slide"
    }
   },
   "source": [
    "## CPython repository https://github.com/python/cpython\n",
    "- easy to compile and setup for development\n",
    "- most important directories: \n",
    "  - Include: header files\n",
    "  - Objects: object implementations, from int to type\n",
    "  - Python: interpreter, bytecode compiler and other essential infrastructure\n",
    "- other:\n",
    "  - Modules: stdlib extension modules\n",
    "  - Lib: Python standard library implemented in Python\n"
   ]
  },
  {
   "cell_type": "markdown",
   "metadata": {
    "slideshow": {
     "slide_type": "slide"
    }
   },
   "source": [
    "## High level overview of running a Python script\n",
    "\\*.py -> compiler -> bytecode -> main iterpreter loop"
   ]
  },
  {
   "cell_type": "markdown",
   "metadata": {
    "slideshow": {
     "slide_type": "subslide"
    }
   },
   "source": [
    "## Compilation\n",
    "In CPython, the compilation from source code to bytecode involves several steps:\n",
    "\n",
    "1. Parse source code into a parse tree (Parser/pgen.c)\n",
    "2. Transform parse tree into an Abstract Syntax Tree (Python/ast.c)\n",
    "3. Transform AST into a Control Flow Graph (Python/compile.c)\n",
    "4. Emit bytecode based on the Control Flow Graph (Python/compile.c)"
   ]
  },
  {
   "cell_type": "markdown",
   "metadata": {
    "slideshow": {
     "slide_type": "subslide"
    }
   },
   "source": [
    "## Let's start with a simple Python script"
   ]
  },
  {
   "cell_type": "code",
   "execution_count": 1,
   "metadata": {
    "slideshow": {
     "slide_type": "subslide"
    }
   },
   "outputs": [],
   "source": [
    "script = \"\"\"\n",
    "G = 1\n",
    "\n",
    "class A:\n",
    "    def __init__(self, func):\n",
    "        self.func = func\n",
    "\n",
    "def func(n):\n",
    "    return G + n\n",
    "\n",
    "\"\"\""
   ]
  },
  {
   "cell_type": "code",
   "execution_count": 2,
   "metadata": {
    "slideshow": {
     "slide_type": "fragment"
    }
   },
   "outputs": [],
   "source": [
    "from ast import parse\n",
    "ast_ = parse(script)"
   ]
  },
  {
   "cell_type": "code",
   "execution_count": 3,
   "metadata": {
    "slideshow": {
     "slide_type": "fragment"
    }
   },
   "outputs": [
    {
     "data": {
      "text/plain": [
       "[<_ast.Assign at 0x7f5e86e06d00>,\n",
       " <_ast.ClassDef at 0x7f5e86e06610>,\n",
       " <_ast.FunctionDef at 0x7f5e86e06940>]"
      ]
     },
     "execution_count": 3,
     "metadata": {},
     "output_type": "execute_result"
    }
   ],
   "source": [
    "ast_.body"
   ]
  },
  {
   "cell_type": "code",
   "execution_count": 4,
   "metadata": {
    "slideshow": {
     "slide_type": "subslide"
    }
   },
   "outputs": [
    {
     "data": {
      "text/plain": [
       "<_ast.BinOp at 0x7f5e86e31160>"
      ]
     },
     "execution_count": 4,
     "metadata": {},
     "output_type": "execute_result"
    }
   ],
   "source": [
    "ast_.body[2].body[0].value"
   ]
  },
  {
   "cell_type": "code",
   "execution_count": 5,
   "metadata": {
    "slideshow": {
     "slide_type": "fragment"
    }
   },
   "outputs": [
    {
     "data": {
      "text/plain": [
       "'__init__'"
      ]
     },
     "execution_count": 5,
     "metadata": {},
     "output_type": "execute_result"
    }
   ],
   "source": [
    "ast_.body[1].body[0].name"
   ]
  },
  {
   "cell_type": "code",
   "execution_count": 6,
   "metadata": {
    "slideshow": {
     "slide_type": "subslide"
    }
   },
   "outputs": [],
   "source": [
    "co = compile(ast_, 'test.py', 'exec')"
   ]
  },
  {
   "cell_type": "code",
   "execution_count": 7,
   "metadata": {
    "slideshow": {
     "slide_type": "fragment"
    }
   },
   "outputs": [
    {
     "data": {
      "text/plain": [
       "{'co_argcount': 0,\n",
       " 'co_cellvars': (),\n",
       " 'co_code': b'd\\x00Z\\x00G\\x00d\\x01d\\x02\\x84\\x00d\\x02\\x83\\x02Z\\x01d\\x03d\\x04\\x84\\x00Z\\x02d\\x05S\\x00',\n",
       " 'co_consts': (1,\n",
       "  <code object A at 0x7f5e86e34240, file \"test.py\", line 4>,\n",
       "  'A',\n",
       "  <code object func at 0x7f5e86e342f0, file \"test.py\", line 8>,\n",
       "  'func',\n",
       "  None),\n",
       " 'co_filename': 'test.py',\n",
       " 'co_firstlineno': 2,\n",
       " 'co_flags': 8256,\n",
       " 'co_freevars': (),\n",
       " 'co_kwonlyargcount': 0,\n",
       " 'co_lnotab': b'\\x04\\x02\\x0e\\x04',\n",
       " 'co_name': '<module>',\n",
       " 'co_names': ('G', 'A', 'func'),\n",
       " 'co_nlocals': 0,\n",
       " 'co_posonlyargcount': 0,\n",
       " 'co_stacksize': 3,\n",
       " 'co_varnames': (),\n",
       " 'replace': <function code.replace(*, co_argcount=-1, co_posonlyargcount=-1, co_kwonlyargcount=-1, co_nlocals=-1, co_stacksize=-1, co_flags=-1, co_firstlineno=-1, co_code=None, co_consts=None, co_names=None, co_varnames=None, co_freevars=None, co_cellvars=None, co_filename=None, co_name=None, co_lnotab=None)>}"
      ]
     },
     "execution_count": 7,
     "metadata": {},
     "output_type": "execute_result"
    }
   ],
   "source": [
    "{code:getattr(co, code) for code in dir(co) if not code.startswith('__')}"
   ]
  },
  {
   "cell_type": "code",
   "execution_count": 8,
   "metadata": {
    "scrolled": true,
    "slideshow": {
     "slide_type": "fragment"
    }
   },
   "outputs": [
    {
     "data": {
      "text/plain": [
       "'test.py'"
      ]
     },
     "execution_count": 8,
     "metadata": {},
     "output_type": "execute_result"
    }
   ],
   "source": [
    "co.co_filename"
   ]
  },
  {
   "cell_type": "code",
   "execution_count": 9,
   "metadata": {
    "slideshow": {
     "slide_type": "subslide"
    }
   },
   "outputs": [
    {
     "data": {
      "text/plain": [
       "b'd\\x00Z\\x00G\\x00d\\x01d\\x02\\x84\\x00d\\x02\\x83\\x02Z\\x01d\\x03d\\x04\\x84\\x00Z\\x02d\\x05S\\x00'"
      ]
     },
     "execution_count": 9,
     "metadata": {},
     "output_type": "execute_result"
    }
   ],
   "source": [
    "co.co_code"
   ]
  },
  {
   "cell_type": "code",
   "execution_count": 10,
   "metadata": {
    "slideshow": {
     "slide_type": "fragment"
    }
   },
   "outputs": [
    {
     "data": {
      "text/plain": [
       "[100,\n",
       " 0,\n",
       " 90,\n",
       " 0,\n",
       " 71,\n",
       " 0,\n",
       " 100,\n",
       " 1,\n",
       " 100,\n",
       " 2,\n",
       " 132,\n",
       " 0,\n",
       " 100,\n",
       " 2,\n",
       " 131,\n",
       " 2,\n",
       " 90,\n",
       " 1,\n",
       " 100,\n",
       " 3,\n",
       " 100,\n",
       " 4,\n",
       " 132,\n",
       " 0,\n",
       " 90,\n",
       " 2,\n",
       " 100,\n",
       " 5,\n",
       " 83,\n",
       " 0]"
      ]
     },
     "execution_count": 10,
     "metadata": {},
     "output_type": "execute_result"
    }
   ],
   "source": [
    "[x for x in co.co_code]"
   ]
  },
  {
   "cell_type": "markdown",
   "metadata": {
    "slideshow": {
     "slide_type": "fragment"
    }
   },
   "source": [
    "We can see what every opcode does in the docs https://docs.python.org/3/library/dis.html"
   ]
  },
  {
   "cell_type": "markdown",
   "metadata": {
    "slideshow": {
     "slide_type": "fragment"
    }
   },
   "source": [
    "- defined in `Include/opcode.h`\n",
    "- opcode 90"
   ]
  },
  {
   "cell_type": "code",
   "execution_count": 11,
   "metadata": {
    "slideshow": {
     "slide_type": "subslide"
    }
   },
   "outputs": [
    {
     "name": "stdout",
     "output_type": "stream",
     "text": [
      "The Zen of Python, by Tim Peters\n",
      "\n",
      "Beautiful is better than ugly.\n",
      "Explicit is better than implicit.\n",
      "Simple is better than complex.\n",
      "Complex is better than complicated.\n",
      "Flat is better than nested.\n",
      "Sparse is better than dense.\n",
      "Readability counts.\n",
      "Special cases aren't special enough to break the rules.\n",
      "Although practicality beats purity.\n",
      "Errors should never pass silently.\n",
      "Unless explicitly silenced.\n",
      "In the face of ambiguity, refuse the temptation to guess.\n",
      "There should be one-- and preferably only one --obvious way to do it.\n",
      "Although that way may not be obvious at first unless you're Dutch.\n",
      "Now is better than never.\n",
      "Although never is often better than *right* now.\n",
      "If the implementation is hard to explain, it's a bad idea.\n",
      "If the implementation is easy to explain, it may be a good idea.\n",
      "Namespaces are one honking great idea -- let's do more of those!\n"
     ]
    }
   ],
   "source": [
    "import this"
   ]
  },
  {
   "cell_type": "code",
   "execution_count": 12,
   "metadata": {
    "slideshow": {
     "slide_type": "subslide"
    }
   },
   "outputs": [],
   "source": [
    "import dis"
   ]
  },
  {
   "cell_type": "code",
   "execution_count": 13,
   "metadata": {
    "slideshow": {
     "slide_type": "fragment"
    }
   },
   "outputs": [
    {
     "name": "stdout",
     "output_type": "stream",
     "text": [
      "  2           0 LOAD_CONST               0 (1)\n",
      "              2 STORE_NAME               0 (G)\n",
      "\n",
      "  4           4 LOAD_BUILD_CLASS\n",
      "              6 LOAD_CONST               1 (<code object A at 0x7f5e86e34240, file \"test.py\", line 4>)\n",
      "              8 LOAD_CONST               2 ('A')\n",
      "             10 MAKE_FUNCTION            0\n",
      "             12 LOAD_CONST               2 ('A')\n",
      "             14 CALL_FUNCTION            2\n",
      "             16 STORE_NAME               1 (A)\n",
      "\n",
      "  8          18 LOAD_CONST               3 (<code object func at 0x7f5e86e342f0, file \"test.py\", line 8>)\n",
      "             20 LOAD_CONST               4 ('func')\n",
      "             22 MAKE_FUNCTION            0\n",
      "             24 STORE_NAME               2 (func)\n",
      "             26 LOAD_CONST               5 (None)\n",
      "             28 RETURN_VALUE\n",
      "\n",
      "Disassembly of <code object A at 0x7f5e86e34240, file \"test.py\", line 4>:\n",
      "  4           0 LOAD_NAME                0 (__name__)\n",
      "              2 STORE_NAME               1 (__module__)\n",
      "              4 LOAD_CONST               0 ('A')\n",
      "              6 STORE_NAME               2 (__qualname__)\n",
      "\n",
      "  5           8 LOAD_CONST               1 (<code object __init__ at 0x7f5e86e10f50, file \"test.py\", line 5>)\n",
      "             10 LOAD_CONST               2 ('A.__init__')\n",
      "             12 MAKE_FUNCTION            0\n",
      "             14 STORE_NAME               3 (__init__)\n",
      "             16 LOAD_CONST               3 (None)\n",
      "             18 RETURN_VALUE\n",
      "\n",
      "Disassembly of <code object __init__ at 0x7f5e86e10f50, file \"test.py\", line 5>:\n",
      "  6           0 LOAD_FAST                1 (func)\n",
      "              2 LOAD_FAST                0 (self)\n",
      "              4 STORE_ATTR               0 (func)\n",
      "              6 LOAD_CONST               0 (None)\n",
      "              8 RETURN_VALUE\n",
      "\n",
      "Disassembly of <code object func at 0x7f5e86e342f0, file \"test.py\", line 8>:\n",
      "  9           0 LOAD_GLOBAL              0 (G)\n",
      "              2 LOAD_FAST                0 (n)\n",
      "              4 BINARY_ADD\n",
      "              6 RETURN_VALUE\n"
     ]
    }
   ],
   "source": [
    "dis.dis(co)"
   ]
  },
  {
   "cell_type": "markdown",
   "metadata": {
    "slideshow": {
     "slide_type": "slide"
    }
   },
   "source": [
    "## Maybe we should start with something easier"
   ]
  },
  {
   "cell_type": "code",
   "execution_count": 14,
   "metadata": {
    "slideshow": {
     "slide_type": "fragment"
    }
   },
   "outputs": [],
   "source": [
    "def f():\n",
    "    ..."
   ]
  },
  {
   "cell_type": "code",
   "execution_count": 15,
   "metadata": {
    "slideshow": {
     "slide_type": "fragment"
    }
   },
   "outputs": [
    {
     "name": "stdout",
     "output_type": "stream",
     "text": [
      "  2           0 LOAD_CONST               0 (None)\n",
      "              2 RETURN_VALUE\n"
     ]
    }
   ],
   "source": [
    "dis.dis(f)"
   ]
  },
  {
   "cell_type": "code",
   "execution_count": 16,
   "metadata": {
    "slideshow": {
     "slide_type": "subslide"
    }
   },
   "outputs": [],
   "source": [
    "def f():\n",
    "    x = 1\n",
    "    return x"
   ]
  },
  {
   "cell_type": "code",
   "execution_count": 17,
   "metadata": {
    "scrolled": true,
    "slideshow": {
     "slide_type": "fragment"
    }
   },
   "outputs": [
    {
     "name": "stdout",
     "output_type": "stream",
     "text": [
      "  2           0 LOAD_CONST               1 (1)\n",
      "              2 STORE_FAST               0 (x)\n",
      "\n",
      "  3           4 LOAD_FAST                0 (x)\n",
      "              6 RETURN_VALUE\n"
     ]
    }
   ],
   "source": [
    "dis.dis(f)"
   ]
  },
  {
   "cell_type": "code",
   "execution_count": 18,
   "metadata": {
    "slideshow": {
     "slide_type": "subslide"
    }
   },
   "outputs": [],
   "source": [
    "class A:\n",
    "        ..."
   ]
  },
  {
   "cell_type": "code",
   "execution_count": 19,
   "metadata": {
    "scrolled": true,
    "slideshow": {
     "slide_type": "fragment"
    }
   },
   "outputs": [],
   "source": [
    "dis.dis(A)"
   ]
  },
  {
   "cell_type": "code",
   "execution_count": 20,
   "metadata": {
    "slideshow": {
     "slide_type": "subslide"
    }
   },
   "outputs": [],
   "source": [
    "def _():\n",
    "    class A:\n",
    "        ..."
   ]
  },
  {
   "cell_type": "code",
   "execution_count": 21,
   "metadata": {
    "slideshow": {
     "slide_type": "fragment"
    }
   },
   "outputs": [
    {
     "name": "stdout",
     "output_type": "stream",
     "text": [
      "  2           0 LOAD_BUILD_CLASS\n",
      "              2 LOAD_CONST               1 (<code object A at 0x7f5e86dd6ea0, file \"<ipython-input-20-a5730c675798>\", line 2>)\n",
      "              4 LOAD_CONST               2 ('A')\n",
      "              6 MAKE_FUNCTION            0\n",
      "              8 LOAD_CONST               2 ('A')\n",
      "             10 CALL_FUNCTION            2\n",
      "             12 STORE_FAST               0 (A)\n",
      "             14 LOAD_CONST               0 (None)\n",
      "             16 RETURN_VALUE\n",
      "\n",
      "Disassembly of <code object A at 0x7f5e86dd6ea0, file \"<ipython-input-20-a5730c675798>\", line 2>:\n",
      "  2           0 LOAD_NAME                0 (__name__)\n",
      "              2 STORE_NAME               1 (__module__)\n",
      "              4 LOAD_CONST               0 ('_.<locals>.A')\n",
      "              6 STORE_NAME               2 (__qualname__)\n",
      "\n",
      "  3           8 LOAD_CONST               1 (None)\n",
      "             10 RETURN_VALUE\n"
     ]
    }
   ],
   "source": [
    "dis.dis(_)"
   ]
  },
  {
   "cell_type": "markdown",
   "metadata": {
    "slideshow": {
     "slide_type": "subslide"
    }
   },
   "source": [
    "## Fun fact: some statements of the Python grammar have no corresponding executable bytecode -- they have only effect in compilation time"
   ]
  },
  {
   "cell_type": "code",
   "execution_count": 22,
   "metadata": {
    "slideshow": {
     "slide_type": "subslide"
    }
   },
   "outputs": [],
   "source": [
    "def _(x=1):\n",
    "    def f():\n",
    "        return x"
   ]
  },
  {
   "cell_type": "code",
   "execution_count": 23,
   "metadata": {
    "scrolled": true,
    "slideshow": {
     "slide_type": "fragment"
    }
   },
   "outputs": [
    {
     "name": "stdout",
     "output_type": "stream",
     "text": [
      "  2           0 LOAD_CLOSURE             0 (x)\n",
      "              2 BUILD_TUPLE              1\n",
      "              4 LOAD_CONST               1 (<code object f at 0x7f5e86dd6a80, file \"<ipython-input-22-14deac161694>\", line 2>)\n",
      "              6 LOAD_CONST               2 ('_.<locals>.f')\n",
      "              8 MAKE_FUNCTION            8 (closure)\n",
      "             10 STORE_FAST               1 (f)\n",
      "             12 LOAD_CONST               0 (None)\n",
      "             14 RETURN_VALUE\n",
      "\n",
      "Disassembly of <code object f at 0x7f5e86dd6a80, file \"<ipython-input-22-14deac161694>\", line 2>:\n",
      "  3           0 LOAD_DEREF               0 (x)\n",
      "              2 RETURN_VALUE\n"
     ]
    }
   ],
   "source": [
    "dis.dis(_)"
   ]
  },
  {
   "cell_type": "code",
   "execution_count": 24,
   "metadata": {
    "slideshow": {
     "slide_type": "subslide"
    }
   },
   "outputs": [],
   "source": [
    "G = 1\n",
    "def _():\n",
    "    return G"
   ]
  },
  {
   "cell_type": "code",
   "execution_count": 25,
   "metadata": {
    "slideshow": {
     "slide_type": "fragment"
    }
   },
   "outputs": [
    {
     "name": "stdout",
     "output_type": "stream",
     "text": [
      "  3           0 LOAD_GLOBAL              0 (G)\n",
      "              2 RETURN_VALUE\n"
     ]
    }
   ],
   "source": [
    "dis.dis(_)"
   ]
  },
  {
   "cell_type": "code",
   "execution_count": 26,
   "metadata": {
    "slideshow": {
     "slide_type": "subslide"
    }
   },
   "outputs": [],
   "source": [
    "x = 1\n",
    "def _():\n",
    "    x += 1  # the same as x = x + 1"
   ]
  },
  {
   "cell_type": "code",
   "execution_count": 27,
   "metadata": {
    "scrolled": false,
    "slideshow": {
     "slide_type": "fragment"
    }
   },
   "outputs": [
    {
     "ename": "UnboundLocalError",
     "evalue": "local variable 'x' referenced before assignment",
     "output_type": "error",
     "traceback": [
      "\u001b[0;31m---------------------------------------------------------------------------\u001b[0m",
      "\u001b[0;31mUnboundLocalError\u001b[0m                         Traceback (most recent call last)",
      "\u001b[0;32m<ipython-input-27-cdd3bb414e5b>\u001b[0m in \u001b[0;36m<module>\u001b[0;34m\u001b[0m\n\u001b[0;32m----> 1\u001b[0;31m \u001b[0m_\u001b[0m\u001b[0;34m(\u001b[0m\u001b[0;34m)\u001b[0m\u001b[0;34m\u001b[0m\u001b[0;34m\u001b[0m\u001b[0m\n\u001b[0m",
      "\u001b[0;32m<ipython-input-26-6e022a51cab5>\u001b[0m in \u001b[0;36m_\u001b[0;34m()\u001b[0m\n\u001b[1;32m      1\u001b[0m \u001b[0mx\u001b[0m \u001b[0;34m=\u001b[0m \u001b[0;36m1\u001b[0m\u001b[0;34m\u001b[0m\u001b[0;34m\u001b[0m\u001b[0m\n\u001b[1;32m      2\u001b[0m \u001b[0;32mdef\u001b[0m \u001b[0m_\u001b[0m\u001b[0;34m(\u001b[0m\u001b[0;34m)\u001b[0m\u001b[0;34m:\u001b[0m\u001b[0;34m\u001b[0m\u001b[0;34m\u001b[0m\u001b[0m\n\u001b[0;32m----> 3\u001b[0;31m     \u001b[0mx\u001b[0m \u001b[0;34m+=\u001b[0m \u001b[0;36m1\u001b[0m  \u001b[0;31m# the same as x = x + 1\u001b[0m\u001b[0;34m\u001b[0m\u001b[0;34m\u001b[0m\u001b[0m\n\u001b[0m",
      "\u001b[0;31mUnboundLocalError\u001b[0m: local variable 'x' referenced before assignment"
     ]
    }
   ],
   "source": [
    "_()"
   ]
  },
  {
   "cell_type": "code",
   "execution_count": 28,
   "metadata": {
    "slideshow": {
     "slide_type": "fragment"
    }
   },
   "outputs": [
    {
     "name": "stdout",
     "output_type": "stream",
     "text": [
      "  3           0 LOAD_FAST                0 (x)\n",
      "              2 LOAD_CONST               1 (1)\n",
      "              4 INPLACE_ADD\n",
      "              6 STORE_FAST               0 (x)\n",
      "              8 LOAD_CONST               0 (None)\n",
      "             10 RETURN_VALUE\n"
     ]
    }
   ],
   "source": [
    "dis.dis(_)"
   ]
  },
  {
   "cell_type": "code",
   "execution_count": 29,
   "metadata": {
    "slideshow": {
     "slide_type": "subslide"
    }
   },
   "outputs": [],
   "source": [
    "x = 1\n",
    "def _():\n",
    "    global x\n",
    "    x += 1"
   ]
  },
  {
   "cell_type": "code",
   "execution_count": 30,
   "metadata": {
    "slideshow": {
     "slide_type": "fragment"
    }
   },
   "outputs": [
    {
     "data": {
      "text/plain": [
       "2"
      ]
     },
     "execution_count": 30,
     "metadata": {},
     "output_type": "execute_result"
    }
   ],
   "source": [
    "_()\n",
    "x"
   ]
  },
  {
   "cell_type": "code",
   "execution_count": 31,
   "metadata": {
    "slideshow": {
     "slide_type": "fragment"
    }
   },
   "outputs": [
    {
     "name": "stdout",
     "output_type": "stream",
     "text": [
      "  4           0 LOAD_GLOBAL              0 (x)\n",
      "              2 LOAD_CONST               1 (1)\n",
      "              4 INPLACE_ADD\n",
      "              6 STORE_GLOBAL             0 (x)\n",
      "              8 LOAD_CONST               0 (None)\n",
      "             10 RETURN_VALUE\n"
     ]
    }
   ],
   "source": [
    "dis.dis(_)"
   ]
  },
  {
   "cell_type": "code",
   "execution_count": 32,
   "metadata": {
    "slideshow": {
     "slide_type": "subslide"
    }
   },
   "outputs": [],
   "source": [
    "def _():\n",
    "    x = 1\n",
    "    def f():\n",
    "        nonlocal x\n",
    "        x += 1"
   ]
  },
  {
   "cell_type": "code",
   "execution_count": 33,
   "metadata": {
    "slideshow": {
     "slide_type": "fragment"
    }
   },
   "outputs": [
    {
     "name": "stdout",
     "output_type": "stream",
     "text": [
      "  2           0 LOAD_CONST               1 (1)\n",
      "              2 STORE_DEREF              0 (x)\n",
      "\n",
      "  3           4 LOAD_CLOSURE             0 (x)\n",
      "              6 BUILD_TUPLE              1\n",
      "              8 LOAD_CONST               2 (<code object f at 0x7f5e86e34190, file \"<ipython-input-32-77d10288b2dd>\", line 3>)\n",
      "             10 LOAD_CONST               3 ('_.<locals>.f')\n",
      "             12 MAKE_FUNCTION            8 (closure)\n",
      "             14 STORE_FAST               0 (f)\n",
      "             16 LOAD_CONST               0 (None)\n",
      "             18 RETURN_VALUE\n",
      "\n",
      "Disassembly of <code object f at 0x7f5e86e34190, file \"<ipython-input-32-77d10288b2dd>\", line 3>:\n",
      "  5           0 LOAD_DEREF               0 (x)\n",
      "              2 LOAD_CONST               1 (1)\n",
      "              4 INPLACE_ADD\n",
      "              6 STORE_DEREF              0 (x)\n",
      "              8 LOAD_CONST               0 (None)\n",
      "             10 RETURN_VALUE\n"
     ]
    }
   ],
   "source": [
    "dis.dis(_)"
   ]
  },
  {
   "cell_type": "code",
   "execution_count": 34,
   "metadata": {
    "slideshow": {
     "slide_type": "subslide"
    }
   },
   "outputs": [],
   "source": [
    "def f():\n",
    "    locals()['m'] = 1\n",
    "    print(locals()['m'])    \n",
    "    print(f'm = {m}')\n"
   ]
  },
  {
   "cell_type": "code",
   "execution_count": 35,
   "metadata": {
    "slideshow": {
     "slide_type": "fragment"
    }
   },
   "outputs": [
    {
     "name": "stdout",
     "output_type": "stream",
     "text": [
      "1\n"
     ]
    },
    {
     "ename": "NameError",
     "evalue": "name 'm' is not defined",
     "output_type": "error",
     "traceback": [
      "\u001b[0;31m---------------------------------------------------------------------------\u001b[0m",
      "\u001b[0;31mNameError\u001b[0m                                 Traceback (most recent call last)",
      "\u001b[0;32m<ipython-input-35-c43e34e6d405>\u001b[0m in \u001b[0;36m<module>\u001b[0;34m\u001b[0m\n\u001b[0;32m----> 1\u001b[0;31m \u001b[0mf\u001b[0m\u001b[0;34m(\u001b[0m\u001b[0;34m)\u001b[0m\u001b[0;34m\u001b[0m\u001b[0;34m\u001b[0m\u001b[0m\n\u001b[0m",
      "\u001b[0;32m<ipython-input-34-50f8e69061f9>\u001b[0m in \u001b[0;36mf\u001b[0;34m()\u001b[0m\n\u001b[1;32m      2\u001b[0m     \u001b[0mlocals\u001b[0m\u001b[0;34m(\u001b[0m\u001b[0;34m)\u001b[0m\u001b[0;34m[\u001b[0m\u001b[0;34m'm'\u001b[0m\u001b[0;34m]\u001b[0m \u001b[0;34m=\u001b[0m \u001b[0;36m1\u001b[0m\u001b[0;34m\u001b[0m\u001b[0;34m\u001b[0m\u001b[0m\n\u001b[1;32m      3\u001b[0m     \u001b[0mprint\u001b[0m\u001b[0;34m(\u001b[0m\u001b[0mlocals\u001b[0m\u001b[0;34m(\u001b[0m\u001b[0;34m)\u001b[0m\u001b[0;34m[\u001b[0m\u001b[0;34m'm'\u001b[0m\u001b[0;34m]\u001b[0m\u001b[0;34m)\u001b[0m\u001b[0;34m\u001b[0m\u001b[0;34m\u001b[0m\u001b[0m\n\u001b[0;32m----> 4\u001b[0;31m     \u001b[0mprint\u001b[0m\u001b[0;34m(\u001b[0m\u001b[0;34mf'm = {m}'\u001b[0m\u001b[0;34m)\u001b[0m\u001b[0;34m\u001b[0m\u001b[0;34m\u001b[0m\u001b[0m\n\u001b[0m",
      "\u001b[0;31mNameError\u001b[0m: name 'm' is not defined"
     ]
    }
   ],
   "source": [
    "f()"
   ]
  },
  {
   "cell_type": "code",
   "execution_count": 36,
   "metadata": {
    "slideshow": {
     "slide_type": "subslide"
    }
   },
   "outputs": [
    {
     "name": "stdout",
     "output_type": "stream",
     "text": [
      "  2           0 LOAD_CONST               1 (1)\n",
      "              2 LOAD_GLOBAL              0 (locals)\n",
      "              4 CALL_FUNCTION            0\n",
      "              6 LOAD_CONST               2 ('m')\n",
      "              8 STORE_SUBSCR\n",
      "\n",
      "  3          10 LOAD_GLOBAL              1 (print)\n",
      "             12 LOAD_GLOBAL              0 (locals)\n",
      "             14 CALL_FUNCTION            0\n",
      "             16 LOAD_CONST               2 ('m')\n",
      "             18 BINARY_SUBSCR\n",
      "             20 CALL_FUNCTION            1\n",
      "             22 POP_TOP\n",
      "\n",
      "  4          24 LOAD_GLOBAL              1 (print)\n",
      "             26 LOAD_CONST               3 ('m = ')\n",
      "             28 LOAD_GLOBAL              2 (m)\n",
      "             30 FORMAT_VALUE             0\n",
      "             32 BUILD_STRING             2\n",
      "             34 CALL_FUNCTION            1\n",
      "             36 POP_TOP\n",
      "             38 LOAD_CONST               0 (None)\n",
      "             40 RETURN_VALUE\n"
     ]
    }
   ],
   "source": [
    "dis.dis(f)"
   ]
  },
  {
   "cell_type": "code",
   "execution_count": 37,
   "metadata": {
    "slideshow": {
     "slide_type": "subslide"
    }
   },
   "outputs": [],
   "source": [
    "def _(x,y):\n",
    "    return x + y"
   ]
  },
  {
   "cell_type": "code",
   "execution_count": 38,
   "metadata": {
    "scrolled": true,
    "slideshow": {
     "slide_type": "fragment"
    }
   },
   "outputs": [
    {
     "name": "stdout",
     "output_type": "stream",
     "text": [
      "  2           0 LOAD_FAST                0 (x)\n",
      "              2 LOAD_FAST                1 (y)\n",
      "              4 BINARY_ADD\n",
      "              6 RETURN_VALUE\n"
     ]
    }
   ],
   "source": [
    "dis.dis(_)"
   ]
  },
  {
   "cell_type": "code",
   "execution_count": 39,
   "metadata": {
    "slideshow": {
     "slide_type": "subslide"
    }
   },
   "outputs": [],
   "source": [
    "def _(x, y):\n",
    "    return x.__add__(y)"
   ]
  },
  {
   "cell_type": "code",
   "execution_count": 40,
   "metadata": {
    "slideshow": {
     "slide_type": "fragment"
    }
   },
   "outputs": [
    {
     "name": "stdout",
     "output_type": "stream",
     "text": [
      "  2           0 LOAD_FAST                0 (x)\n",
      "              2 LOAD_METHOD              0 (__add__)\n",
      "              4 LOAD_FAST                1 (y)\n",
      "              6 CALL_METHOD              1\n",
      "              8 RETURN_VALUE\n"
     ]
    }
   ],
   "source": [
    "dis.dis(_)"
   ]
  },
  {
   "cell_type": "markdown",
   "metadata": {
    "slideshow": {
     "slide_type": "fragment"
    }
   },
   "source": [
    "Python doesn't know what `x` and `y` is. Python just tries it at runtime"
   ]
  },
  {
   "cell_type": "markdown",
   "metadata": {
    "slideshow": {
     "slide_type": "subslide"
    }
   },
   "source": [
    "## Main interpreter loop vs. performance"
   ]
  },
  {
   "cell_type": "markdown",
   "metadata": {
    "slideshow": {
     "slide_type": "fragment"
    }
   },
   "source": [
    "A common misconception is that `__add__` is the same as the `+` operator (etc.)"
   ]
  },
  {
   "cell_type": "code",
   "execution_count": 41,
   "metadata": {
    "slideshow": {
     "slide_type": "fragment"
    }
   },
   "outputs": [],
   "source": [
    "x = 1"
   ]
  },
  {
   "cell_type": "code",
   "execution_count": 42,
   "metadata": {
    "slideshow": {
     "slide_type": "fragment"
    }
   },
   "outputs": [
    {
     "name": "stdout",
     "output_type": "stream",
     "text": [
      "33.7 ns ± 0.656 ns per loop (mean ± std. dev. of 7 runs, 10000000 loops each)\n"
     ]
    }
   ],
   "source": [
    "%timeit x + x"
   ]
  },
  {
   "cell_type": "code",
   "execution_count": 43,
   "metadata": {
    "slideshow": {
     "slide_type": "fragment"
    }
   },
   "outputs": [
    {
     "name": "stdout",
     "output_type": "stream",
     "text": [
      "83.9 ns ± 2.1 ns per loop (mean ± std. dev. of 7 runs, 10000000 loops each)\n"
     ]
    }
   ],
   "source": [
    "%timeit x.__add__(x)"
   ]
  },
  {
   "cell_type": "code",
   "execution_count": 44,
   "metadata": {
    "slideshow": {
     "slide_type": "subslide"
    }
   },
   "outputs": [
    {
     "name": "stdout",
     "output_type": "stream",
     "text": [
      "6.57 ns ± 0.192 ns per loop (mean ± std. dev. of 7 runs, 100000000 loops each)\n"
     ]
    }
   ],
   "source": [
    "%timeit '1' + '1'"
   ]
  },
  {
   "cell_type": "code",
   "execution_count": 45,
   "metadata": {
    "slideshow": {
     "slide_type": "fragment"
    }
   },
   "outputs": [
    {
     "name": "stdout",
     "output_type": "stream",
     "text": [
      "106 ns ± 3.52 ns per loop (mean ± std. dev. of 7 runs, 10000000 loops each)\n"
     ]
    }
   ],
   "source": [
    "%timeit '1'.__add__('1')"
   ]
  },
  {
   "cell_type": "markdown",
   "metadata": {
    "slideshow": {
     "slide_type": "subslide"
    }
   },
   "source": [
    "# Why do we see such difference??\n",
    "\n"
   ]
  },
  {
   "cell_type": "markdown",
   "metadata": {
    "slideshow": {
     "slide_type": "fragment"
    }
   },
   "source": [
    "## DEMO TIME!!!\n",
    "Goto Python/ceval.c"
   ]
  },
  {
   "cell_type": "code",
   "execution_count": 46,
   "metadata": {},
   "outputs": [
    {
     "ename": "SyntaxError",
     "evalue": "invalid syntax (<ipython-input-46-033d5ec356b0>, line 1)",
     "output_type": "error",
     "traceback": [
      "\u001b[0;36m  File \u001b[0;32m\"<ipython-input-46-033d5ec356b0>\"\u001b[0;36m, line \u001b[0;32m1\u001b[0m\n\u001b[0;31m    StackFrames, every frame has 3 stacks,  every function has a separate frame, PyObjectVar, structural subtyping\u001b[0m\n\u001b[0m                       ^\u001b[0m\n\u001b[0;31mSyntaxError\u001b[0m\u001b[0;31m:\u001b[0m invalid syntax\n"
     ]
    }
   ],
   "source": [
    "StackFrames, every frame has 3 stacks,  every function has a separate frame, PyObjectVar, structural subtyping"
   ]
  },
  {
   "cell_type": "code",
   "execution_count": null,
   "metadata": {},
   "outputs": [],
   "source": []
  }
 ],
 "metadata": {
  "celltoolbar": "Slideshow",
  "kernelspec": {
   "display_name": "Python 3",
   "language": "python",
   "name": "python3"
  },
  "language_info": {
   "codemirror_mode": {
    "name": "ipython",
    "version": 3
   },
   "file_extension": ".py",
   "mimetype": "text/x-python",
   "name": "python",
   "nbconvert_exporter": "python",
   "pygments_lexer": "ipython3",
   "version": "3.8.0"
  }
 },
 "nbformat": 4,
 "nbformat_minor": 4
}
